CombineHarvesterFlow/__init__.py
CombineHarvesterFlow/combine.py
CombineHarvesterFlow/harvest.py
CombineHarvesterFlow/utils.py
CombineHarvesterFlow-1.0.0.dist-info/LICENSE
CombineHarvesterFlow-1.0.0.dist-info/METADATA
CombineHarvesterFlow-1.0.0.dist-info/WHEEL
CombineHarvesterFlow-1.0.0.dist-info/top_level.txt
CombineHarvesterFlow-1.0.0.dist-info/RECORD
