Metadata-Version: 2.1
Name: CombineHarvesterFlow
Version: 1.0.0
Summary: Harvest and combine chains from different data sets
Author: Peter Taylor
Author-email: taylor.4264@osu.edu
License: GNU General Public License v3.0
Project-URL: Bug Reports, https://github.com/pltaylor16/CombineHarvesterFlow/issues
Project-URL: Source, https://github.com/pltaylor16/CombineHarvesterFlow
Requires-Python: >=3.10
License-File: LICENSE
Requires-Dist: numpy
Requires-Dist: scipy <=1.12.0
Requires-Dist: jax
Requires-Dist: flowjax
Requires-Dist: tqdm
Requires-Dist: equinox
Provides-Extra: dev
Requires-Dist: pytest ; extra == 'dev'
Requires-Dist: flake8 ; extra == 'dev'
Requires-Dist: bump2version ; extra == 'dev'
Provides-Extra: pub
Requires-Dist: build ; extra == 'pub'
Requires-Dist: twine ; extra == 'pub'
